antlr4_tool_runner.py
antlr4_tools-0.2.1.dist-info/LICENSE
antlr4_tools-0.2.1.dist-info/METADATA
antlr4_tools-0.2.1.dist-info/WHEEL
antlr4_tools-0.2.1.dist-info/entry_points.txt
antlr4_tools-0.2.1.dist-info/top_level.txt
antlr4_tools-0.2.1.dist-info/RECORD
